positive_tool/__init__.py
positive_tool/__main__.py
positive_tool/pt.py
positive_tool/verify.py
positive_tool/exceptions/__init__.py
positive_tool/exceptions/exception_arg.py
positive_tool/exceptions/exception_pt.py
positive_tool/exceptions/exceptions.py
positive_tool/exceptions/positive_tool_exception.py
positive_tool-0.7.4.dist-info/licenses/LICENSE
positive_tool-0.7.4.dist-info/METADATA
positive_tool-0.7.4.dist-info/WHEEL
positive_tool-0.7.4.dist-info/top_level.txt
positive_tool-0.7.4.dist-info/RECORD
