Metadata-Version: 2.4
Name: positive-tool
Version: 0.7.4
Summary: `positive_tool` 一個輔助開發的 Python 工具模組。目標提供實用的工具
License: GNU AFFERO GENERAL PUBLIC LICENSE
Project-URL: Homepage, https://github.com/TW0hank0/positive_tool
Project-URL: Repository, https://github.com/TW0hank0/positive_tool
Requires-Python: >=3.11
License-File: LICENSE
Requires-Dist: rich==14.3.1
Provides-Extra: test
Requires-Dist: pytest>=9.0.2; extra == "test"
Requires-Dist: pytest-cov>=4.0.0; extra == "test"
Provides-Extra: build
Requires-Dist: twine; extra == "build"
Dynamic: license-file
